client/__init__.py
client/add_contact.py
client/client.py
client/client_gui.py
client/del_contact.py
client/errors.py
client/main_window_conv.py
client/start_dialog.py
database/__init__.py
database/function.py
database/models.py
log_conf/__init__.py
log_conf/client_log_config.py
log_conf/server_log_config.py
gb_test_client-0.0.1.dist-info/METADATA
gb_test_client-0.0.1.dist-info/WHEEL
gb_test_client-0.0.1.dist-info/top_level.txt
gb_test_client-0.0.1.dist-info/RECORD
