Metadata-Version: 2.1
Name: gb-test-client
Version: 0.0.1
Summary: PyQt messenger Client
Home-page: UNKNOWN
Author: Klark Charlz
Author-email: klark.charlz@mail.ru
License: UNKNOWN
Platform: UNKNOWN
Requires-Dist: PyQt5
Requires-Dist: sqlalchemy
Requires-Dist: pycryptodome
Requires-Dist: pycryptodomex
